setup.py
distributions/Binomialdistribution.py
distributions/Gaussiandistribution.py
distributions/Generaldistribution.py
distributions/__init__.py
macias_distributions.egg-info/PKG-INFO
macias_distributions.egg-info/SOURCES.txt
macias_distributions.egg-info/dependency_links.txt
macias_distributions.egg-info/not-zip-safe
macias_distributions.egg-info/top_level.txt